easygae.py
easygae-0.1.dist-info/DESCRIPTION.rst
easygae-0.1.dist-info/METADATA
easygae-0.1.dist-info/RECORD
easygae-0.1.dist-info/WHEEL
easygae-0.1.dist-info/metadata.json
easygae-0.1.dist-info/top_level.txt
