Metadata-Version: 2.0
Name: easygae
Version: 0.1
Summary: Painless Google App Engine Testing - Nose2 Plugin
Home-page: https://github.com/nicholasamorim/easygae
Author: Nicholas Amorim
Author-email: nicholas@alienretro.com
License: MIT
Keywords: unittest testing gae appengine nose2 app engine
Platform: UNKNOWN
Classifier: Development Status :: 3 - Alpha
Classifier: Environment :: Console
Classifier: Intended Audience :: Developers
Classifier: License :: OSI Approved :: MIT License
Classifier: Programming Language :: Python
Classifier: Programming Language :: Python :: 2
Classifier: Programming Language :: Python :: 2.7
Classifier: Topic :: Software Development :: Libraries
Classifier: Topic :: Software Development :: Libraries :: Python Modules
Classifier: Topic :: Software Development :: Testing
Requires-Dist: nose2
